freeds/__init__.py
freeds/cli/cli.py
freeds/cli/commands/__init__.py
freeds/cli/commands/dc.py
freeds/cli/commands/env.py
freeds/cli/commands/nb.py
freeds/cli/commands/selfcheck.py
freeds/cli/commands/stack.py
freeds/cli/helpers/__init__.py
freeds/cli/helpers/notebook.py
freeds/cli/helpers/stackrunner.py
freeds/cli/helpers/stackutils.py
freeds/config/__init__.py
freeds/config/api/__init__.py
freeds/config/api/config_api.py
freeds/config/config.py
freeds/config/file/__init__.py
freeds/config/file/config_classes.py
freeds/config/file/config_file.py
freeds/notebooks/100.basics/a.hello_world.ipynb
freeds/notebooks/300.spark/a.spark_plain.ipynb
freeds/notebooks/300.spark/b.spark_iceberg.ipynb
freeds/notebooks/template.ipynb
freeds/s3/__init__.py
freeds/s3/s3.py
freeds/selfcheck/__init__.py
freeds/selfcheck/airflow_checks.py
freeds/selfcheck/check_classes.py
freeds/selfcheck/directory_checks.py
freeds/selfcheck/docker_checks.py
freeds/selfcheck/network_checks.py
freeds/selfcheck/notebook_checks.py
freeds/selfcheck/plugin_classes.py
freeds/selfcheck/s3_checks.py
freeds/setup/__init__.py
freeds/setup/main.py
freeds/setup/setup_credentials.py
freeds/setup/setup_directory.py
freeds/setup/setup_docker.py
freeds/setup/utils.py
freeds/spark/__init__.py
freeds/spark/spark.py
freeds/utils/__init__.py
freeds/utils/dates.py
freeds/utils/log.py
freeds/utils/root_config.py
freeds-0.2.25.dist-info/LICENSE
freeds-0.2.25.dist-info/METADATA
freeds-0.2.25.dist-info/WHEEL
freeds-0.2.25.dist-info/entry_points.txt
freeds-0.2.25.dist-info/RECORD
